microtinygrad/__init__.py
microtinygrad/example.py
microtinygrad-0.0.1.dist-info/LICENSE
microtinygrad-0.0.1.dist-info/METADATA
microtinygrad-0.0.1.dist-info/WHEEL
microtinygrad-0.0.1.dist-info/top_level.txt
microtinygrad-0.0.1.dist-info/RECORD
