Metadata-Version: 2.1
Name: microtinygrad
Version: 0.0.1
Summary: tiny nn library that allows you to train classification neural networks
Author-email: Example Author <cakuang123@gmail.com>
Project-URL: Homepage, https://github.com/cakuang1/microtinygrad
Classifier: Programming Language :: Python :: 3
Classifier: License :: OSI Approved :: MIT License
Classifier: Operating System :: OS Independent
Requires-Python: >=3.7
License-File: LICENSE
